basiccaculatorsumit/__init__.py
basiccalculatorsumit-0.1.dist-info/LICENCE.txt
basiccalculatorsumit-0.1.dist-info/METADATA
basiccalculatorsumit-0.1.dist-info/WHEEL
basiccalculatorsumit-0.1.dist-info/top_level.txt
basiccalculatorsumit-0.1.dist-info/RECORD
